{"type": "Feature", "id": 12510390, "geometry": {"type": "Point", "coordinates": [48.9156, 39.087799]}, "properties": {"woe:id": 12510390, "woe:parent_id": 1951953, "woe:name": "Narimanovka South Airport", "woe:placetype": 14, "woe:placetype_name": "Airport", "woe:lang": "ENG", "iso:country": "AZ", "meta:provider": ["geoplanet:7.3.1", "geoplanet:7.3.2", "geoplanet:7.4.0", "geoplanet:7.4.1", "geoplanet:7.5.1", "geoplanet:7.5.2", "geoplanet:7.6.0", "geoplanet:7.8.1", "geoplanet:7.9.0", "geoplanet:7.10.0", "geoplanet:8.0.0", "woeplanet:8.0.0"], "meta:indexed": "2020-08-20T20:27:34.455187", "meta:updated": "2020-10-14T11:52:04.394067", "woe:hierarchy": {"continent": 24865671, "country": 23424741, "town": 0, "planet": 1, "county": 0, "suburb": 0, "state": 20070263, "region": 0, "localadmin": 0}, "woe:timezone_id": 28350813, "woe:hash": "tnfy35eqbjfg", "woe:centroid": [48.9156, 39.087799], "geom:latitude": 39.087799, "geom:longitude": 48.9156, "geom:hash": "tnfy35eqbjfg", "woe:latitude": 39.087799, "geom:centroid": [48.9156, 39.087799], "woe:longitude": 48.9156, "woe:repo": "woeplanet-airport-az", "geom:area": 0.0, "woe:scale": 19}}