{"type": "Feature", "id": 12510401, "geometry": {"type": "Point", "coordinates": [48.857498, 39.5033]}, "properties": {"woe:id": 12510401, "woe:parent_id": 1952018, "woe:name": "Sarvan Airport", "woe:placetype": 14, "woe:placetype_name": "Airport", "woe:lang": "ENG", "iso:country": "AZ", "meta:provider": ["geoplanet:7.3.1", "geoplanet:7.3.2", "geoplanet:7.4.0", "geoplanet:7.4.1", "geoplanet:7.5.1", "geoplanet:7.5.2", "geoplanet:7.6.0", "geoplanet:7.8.1", "geoplanet:7.9.0", "geoplanet:7.10.0", "geoplanet:8.0.0", "woeplanet:8.0.0"], "meta:indexed": "2020-08-20T20:27:34.464105", "meta:updated": "2020-10-14T11:52:04.368740", "woe:hierarchy": {"continent": 24865671, "country": 23424741, "town": 0, "planet": 1, "county": 0, "suburb": 0, "state": 20070280, "region": 0, "localadmin": 0}, "woe:timezone_id": 28350813, "woe:hash": "tp48xz2gqhyg", "woe:centroid": [48.857498, 39.5033], "geom:latitude": 39.5033, "geom:longitude": 48.857498, "geom:hash": "tp48xz2gqhyg", "woe:latitude": 39.5033, "geom:centroid": [48.857498, 39.5033], "woe:longitude": 48.857498, "woe:repo": "woeplanet-airport-az", "geom:area": 0.0, "woe:scale": 19}}